carehq
