Metadata-Version: 2.1
Name: carehq
Version: 0.1.2
Summary: CareHQ API Client for Python.
Home-page: https://github.com/CareHQ/carehq-python
Author: Anthony Blackshaw
Author-email: ant@crmhq.co.uk
Maintainer: Anthony Blackshaw
Maintainer-email: ant@crmhq.co.uk
License: MIT
Keywords: carehq
Platform: UNKNOWN
Classifier: Development Status :: 4 - Beta
Classifier: Intended Audience :: Developers
Classifier: Topic :: Database
Classifier: License :: OSI Approved :: MIT License
Classifier: Operating System :: MacOS :: MacOS X
Classifier: Operating System :: Microsoft :: Windows
Classifier: Operating System :: POSIX
Classifier: Programming Language :: Python :: 3.7
License-File: LICENSE
